environments/build_images.py
examples/simplified_backend_demo.py
pantheon/__init__.py
pantheon/toolsets/__init__.py
pantheon/toolsets/__main__.py
pantheon/toolsets/bio/__init__.py
pantheon/toolsets/bio/api_monitor.py
pantheon/toolsets/bio/api_visualizer.py
pantheon/toolsets/bio/gene_agent.py
pantheon/toolsets/bio/atac/__init__.py
pantheon/toolsets/bio/atac/__main__.py
pantheon/toolsets/bio/atac/analysis.py
pantheon/toolsets/bio/atac/upstream.py
pantheon/toolsets/bio/dock/__init__.py
pantheon/toolsets/bio/dock/dock.py
pantheon/toolsets/bio/dock/prepare_gpf.py
pantheon/toolsets/bio/gene_agent_deps/__init__.py
pantheon/toolsets/bio/gene_agent_deps/worker.py
pantheon/toolsets/bio/gene_agent_deps/worker_pantheon.py
pantheon/toolsets/bio/gene_agent_deps/apis/__init__.py
pantheon/toolsets/bio/gene_agent_deps/apis/get_complex_for_gene_set.py
pantheon/toolsets/bio/gene_agent_deps/apis/get_disease_for_single_gene.py
pantheon/toolsets/bio/gene_agent_deps/apis/get_domain_for_single_gene.py
pantheon/toolsets/bio/gene_agent_deps/apis/get_enrichment_for_gene_set.py
pantheon/toolsets/bio/gene_agent_deps/apis/get_gene_summary_for_single_gene.py
pantheon/toolsets/bio/gene_agent_deps/apis/get_interactions_for_gene_set.py
pantheon/toolsets/bio/gene_agent_deps/apis/get_pathway_for_gene_set.py
pantheon/toolsets/bio/gene_agent_deps/apis/get_pubmed_articles.py
pantheon/toolsets/bio/hic/__init__.py
pantheon/toolsets/bio/hic/__main__.py
pantheon/toolsets/bio/hic/analysis.py
pantheon/toolsets/bio/hic/upstream.py
pantheon/toolsets/bio/rna/__init__.py
pantheon/toolsets/bio/rna/__main__.py
pantheon/toolsets/bio/rna/analysis.py
pantheon/toolsets/bio/rna/upstream.py
pantheon/toolsets/bio/scatac/__init__.py
pantheon/toolsets/bio/scatac/analysis.py
pantheon/toolsets/bio/scatac/base.py
pantheon/toolsets/bio/scatac/upstream.py
pantheon/toolsets/bio/scrna/__init__.py
pantheon/toolsets/bio/scrna/analysis_anno.py
pantheon/toolsets/bio/scrna/base.py
pantheon/toolsets/bio/scrna/upstream.py
pantheon_toolsets-0.5.3.dist-info/METADATA
pantheon_toolsets-0.5.3.dist-info/WHEEL
pantheon_toolsets-0.5.3.dist-info/top_level.txt
pantheon_toolsets-0.5.3.dist-info/RECORD
