Metadata-Version: 2.4
Name: pantheon-toolsets
Version: 0.5.3
Summary: Distributed toolsets for pantheon-agents, provide service via magique message transfer server.
Author-email: Weize Xu <vet.xwz@gmail.com>
License: MIT
Requires-Python: >=3.10
Requires-Dist: magique>=0.6.7
Requires-Dist: executor-engine>=0.3.3
Requires-Dist: diskcache
Requires-Dist: httpx>=0.28.1
Requires-Dist: fire>=0.7.0
Requires-Dist: crawl4ai>=0.5.0
Requires-Dist: loguru>=0.7.3
Requires-Dist: openai>=1.58.1
Requires-Dist: matplotlib>=3.10.3
Requires-Dist: fastmcp>=2.11.0
Requires-Dist: ddgs>=9.5.2
Requires-Dist: pandas
Requires-Dist: hypha_rpc
Requires-Dist: nats-py>=2.6.0
Requires-Dist: cloudpickle>=3.0.0
Provides-Extra: dev
Requires-Dist: pytest-asyncio>=0.24.0; extra == "dev"
Requires-Dist: pytest>=8.3.4; extra == "dev"
Requires-Dist: pytest-cov>=6.0.0; extra == "dev"
